[{"menu_id": "com.samsung.android.lool__title_storage", "score": 32417}, {"menu_id": "com.android.settings__android_auto_connections_settings", "score": 25121}, {"menu_id": "com.samsung.android.lool__title_battery", "score": 24558}, {"menu_id": "com.android.settings__date_time_settings", "score": 21807}, {"menu_id": "com.android.settings__wifi_ap_settings", "score": 17532}, {"menu_id": "com.android.settings__virtual_keyboard_pref", "score": 17452}, {"menu_id": "com.android.settings__sec_font_size", "score": 17431}, {"menu_id": "com.android.settings__finger_scanner", "score": 16263}, {"menu_id": "com.android.settings__enable_now", "score": 16041}, {"menu_id": "com.android.settings__lock_settings_screen", "score": 15305}, {"menu_id": "com.samsung.android.messaging__pref_key_spam_messages_manager", "score": 14776}, {"menu_id": "com.android.settings__always_on_screen", "score": 13326}, {"menu_id": "com.android.settings__configure_notification_settings", "score": 12937}, {"menu_id": "com.android.settings__bluetooth_settings", "score": 12781}, {"menu_id": "com.samsung.android.honeyboard__top_level_keyboard_settings_main", "score": 12755}, {"menu_id": "com.android.settings__data_usage_settings", "score": 12696}, {"menu_id": "com.android.settings__lock_screen_menu_notifications", "score": 12424}, {"menu_id": "com.android.settings__sec_apps_screen", "score": 12275}, {"menu_id": "com.android.settings__screen_timeout", "score": 12112}, {"menu_id": "com.android.settings__top_level_wallpaper_for_search", "score": 10457}, {"menu_id": "com.android.settings__default_apps", "score": 10244}, {"menu_id": "com.android.settings__screen_mode", "score": 9314}, {"menu_id": "com.samsung.android.app.smartcapture__key_screenshots_and_recorder", "score": 8966}, {"menu_id": "com.android.settings__brief_popup_style_settings", "score": 8801}, {"menu_id": "com.samsung.android.app.telephonyui__VOICE_MAIL", "score": 8643}, {"menu_id": "com.android.settings__network_reset_settings", "score": 8558}, {"menu_id": "com.android.settings__increse_touch_sensetivity", "score": 8529}, {"menu_id": "com.android.settings__wifi_hs20_profile", "score": 8508}, {"menu_id": "com.android.settings__wireless_settings", "score": 8457}, {"menu_id": "com.android.settings__default_autofill", "score": 8450}, {"menu_id": "com.samsung.android.messaging__top_level_messages_settings_main_screen", "score": 8342}, {"menu_id": "com.samsung.android.forest__key_wellbeing_wind_down", "score": 8320}, {"menu_id": "com.samsung.android.lool__title_device_care", "score": 8166}, {"menu_id": "com.samsung.android.app.galaxyfinder__key_show_downloads_screenshots", "score": 7630}, {"menu_id": "com.android.settings__simcard_management", "score": 7589}, {"menu_id": "com.samsung.android.lool__key_battery_charging_menu_super_fast_cable_charge", "score": 7510}, {"menu_id": "com.android.settings__clock_style_pref", "score": 7312}, {"menu_id": "com.android.settings__battery_info", "score": 6570}, {"menu_id": "com.android.settings__wifi_settings", "score": 6032}, {"menu_id": "com.samsung.android.lool__key_battery_charging_menu_fast_cable_charge", "score": 5928}, {"menu_id": "com.android.settings__connections_settings", "score": 5915}, {"menu_id": "com.android.settings__ring_volume", "score": 5821}, {"menu_id": "com.android.settings__mobile_network_settings", "score": 5782}, {"menu_id": "com.samsung.android.app.contacts__key_contacts_trash", "score": 5701}, {"menu_id": "com.android.settings__vpn_settings", "score": 5687}, {"menu_id": "com.android.settings__edge_screen", "score": 5673}, {"menu_id": "com.android.settings__bixby_volume", "score": 5594}, {"menu_id": "com.android.settings__account_preference", "score": 5578}, {"menu_id": "com.sec.unifiedwfc__WFCSETTING_RAW_KEY", "score": 5425}, {"menu_id": "com.samsung.android.messaging__pref_sms_settings", "score": 5421}]